.gitignore
build.py
nucliadb_protos-6.11.1.post5854.dist-info/METADATA
nucliadb_protos-6.11.1.post5854.dist-info/WHEEL
nucliadb_protos-6.11.1.post5854.dist-info/entry_points.txt
nucliadb_protos/audit_pb2.py
nucliadb_protos/audit_pb2.pyi
nucliadb_protos/backups_pb2.py
nucliadb_protos/backups_pb2.pyi
nucliadb_protos/backups_pb2_grpc.py
nucliadb_protos/backups_pb2_grpc.pyi
nucliadb_protos/dataset_pb2.py
nucliadb_protos/dataset_pb2.pyi
nucliadb_protos/kb_usage_pb2.py
nucliadb_protos/kb_usage_pb2.pyi
nucliadb_protos/knowledgebox_pb2.py
nucliadb_protos/knowledgebox_pb2.pyi
nucliadb_protos/migrations_pb2.py
nucliadb_protos/migrations_pb2.pyi
nucliadb_protos/py.typed
nucliadb_protos/resources_pb2.py
nucliadb_protos/resources_pb2.pyi
nucliadb_protos/standalone_pb2.py
nucliadb_protos/standalone_pb2.pyi
nucliadb_protos/standalone_pb2_grpc.py
nucliadb_protos/standalone_pb2_grpc.pyi
nucliadb_protos/train_pb2.py
nucliadb_protos/train_pb2.pyi
nucliadb_protos/train_pb2_grpc.py
nucliadb_protos/train_pb2_grpc.pyi
nucliadb_protos/utils_pb2.py
nucliadb_protos/utils_pb2.pyi
nucliadb_protos/writer_pb2.py
nucliadb_protos/writer_pb2.pyi
nucliadb_protos/writer_pb2_grpc.py
nucliadb_protos/writer_pb2_grpc.pyi
nucliadb_protos-6.11.1.post5854.dist-info/RECORD
